{
  "generated_at": "2026-05-23T19:26:11.917197",
  "oos_start": "2022-01-01",
  "oos_end": "2026-05-21",
  "paper_mode": true,
  "v3_comparison": {
    "label": "BREAKTHROUGH-v3 (confluence + ratchet + MR)",
    "total_ret": 81.04,
    "ann_ret": 14.5,
    "net_after_tax": 11.6,
    "win_rate": 48.9,
    "max_dd": -20.76,
    "sharpe": 0.6,
    "n_trades": 94,
    "avg_hold": 62.9,
    "annual": {
      "2022": -10.4,
      "2023": 51.4,
      "2024": 50.1,
      "2025": -13.0,
      "2026": 2.2
    },
    "mom_trades": 41,
    "mr_trades": 53,
    "swing_trades": 0,
    "mom_win_rate": 46.3,
    "mr_win_rate": 50.9,
    "swing_win_rate": 0.0,
    "swing_avg_hold": 0.0,
    "cash_yield_total": 76.6,
    "ratchet_dist": {
      "0": 31,
      "1": 6,
      "2": 4
    }
  },
  "v4_behavioral": {
    "label": "BEHAVIORAL-v4 (v3 + behavioral + swing trade)",
    "total_ret": 67.82,
    "ann_ret": 12.54,
    "net_after_tax": 10.03,
    "win_rate": 46.0,
    "max_dd": -23.51,
    "sharpe": 0.494,
    "n_trades": 324,
    "avg_hold": 22.0,
    "annual": {
      "2022": 9.2,
      "2023": 22.8,
      "2024": 46.0,
      "2025": -13.6,
      "2026": -0.8
    },
    "mom_trades": 33,
    "mr_trades": 57,
    "swing_trades": 234,
    "mom_win_rate": 42.4,
    "mr_win_rate": 49.1,
    "swing_win_rate": 45.7,
    "swing_avg_hold": 7.4,
    "cash_yield_total": 86.5,
    "ratchet_dist": {
      "0": 26,
      "1": 2,
      "2": 5
    }
  },
  "targets": {
    "net_annual_pct": 20.0,
    "win_rate_pct": 50.0,
    "max_dd_pct": -10.0,
    "sharpe": 1.5
  },
  "v4_achieved": {
    "net_annual_pct": 10.03,
    "win_rate_pct": 46.0,
    "max_dd_pct": -23.51,
    "sharpe": 0.494
  }
}