{"nodes": [{"id": "container", "label": "container.py", "file_type": "code", "source_file": "core/system/container.py", "source_location": "L1"}, {"id": "container_servicecontainer", "label": "ServiceContainer", "file_type": "code", "source_file": "core/system/container.py", "source_location": "L20"}, {"id": "container_servicecontainer_new", "label": ".__new__()", "file_type": "code", "source_file": "core/system/container.py", "source_location": "L29"}, {"id": "container_servicecontainer_register", "label": ".register()", "file_type": "code", "source_file": "core/system/container.py", "source_location": "L39"}, {"id": "container_rationale_40", "label": "Direct slot assignment.          Crash early if service name is invalid (Strict", "file_type": "rationale", "source_file": "core/system/container.py", "source_location": "L40"}], "edges": [{"source": "container", "target": "logging", "relation": "imports", "confidence": "EXTRACTED", "source_file": "core/system/container.py", "source_location": "L1", "weight": 1.0}, {"source": "container", "target": "typing", "relation": "imports_from", "confidence": "EXTRACTED", "source_file": "core/system/container.py", "source_location": "L2", "weight": 1.0}, {"source": "container", "target": "container_servicecontainer", "relation": "contains", "confidence": "EXTRACTED", "source_file": "core/system/container.py", "source_location": "L20", "weight": 1.0}, {"source": "container_servicecontainer", "target": "container_servicecontainer_new", "relation": "method", "confidence": "EXTRACTED", "source_file": "core/system/container.py", "source_location": "L29", "weight": 1.0}, {"source": "container_servicecontainer", "target": "container_servicecontainer_register", "relation": "method", "confidence": "EXTRACTED", "source_file": "core/system/container.py", "source_location": "L39", "weight": 1.0}, {"source": "container_rationale_40", "target": "container_servicecontainer_register", "relation": "rationale_for", "confidence": "EXTRACTED", "source_file": "core/system/container.py", "source_location": "L40", "weight": 1.0}]}